py_discord_db_management/__init__.py
py_discord_db_management/dbpyman.py
py_discord_db_management/classes/__init__.py
py_discord_db_management/classes/column.py
py_discord_db_management/classes/database.py
py_discord_db_management/classes/table.py
py_discord_db_management/views/__init__.py
py_discord_db_management/views/table_add_data_view.py
py_discord_db_management/views/table_categories_view.py
py_discord_db_management/views/table_overview_view.py
dbpyman-1.0.0.dist-info/LICENSE
dbpyman-1.0.0.dist-info/METADATA
dbpyman-1.0.0.dist-info/WHEEL
dbpyman-1.0.0.dist-info/top_level.txt
dbpyman-1.0.0.dist-info/RECORD
