Metadata-Version: 2.1
Name: dbpyman
Version: 1.0.0
Summary: A package used to modify & view your MySQL database data dynamically
Author-email: JanikCodes <janiksielaff@gmx.de>
Project-URL: Homepage, https://github.com/JanikCodes/py_discord_db_management
Project-URL: Bug Tracker, https://github.com/JanikCodes/py_discord_db_management/issues
Classifier: Programming Language :: Python :: 3
Classifier: License :: OSI Approved :: MIT License
Classifier: Operating System :: OS Independent
Requires-Python: >=3.10
License-File: LICENSE
